setuptools_rust/__init__.py
setuptools_rust/_utils.py
setuptools_rust/build.py
setuptools_rust/clean.py
setuptools_rust/command.py
setuptools_rust/extension.py
setuptools_rust/py.typed
setuptools_rust/rustc_info.py
setuptools_rust/setuptools_ext.py
setuptools_rust/version.py
setuptools_rust-1.10.2.dist-info/LICENSE
setuptools_rust-1.10.2.dist-info/METADATA
setuptools_rust-1.10.2.dist-info/WHEEL
setuptools_rust-1.10.2.dist-info/entry_points.txt
setuptools_rust-1.10.2.dist-info/top_level.txt
setuptools_rust-1.10.2.dist-info/zip-safe
setuptools_rust-1.10.2.dist-info/RECORD
