Metadata-Version: 2.1
Name: setuptools-rust
Version: 1.10.2
Summary: Setuptools Rust extension plugin
Author-email: Nikolay Kim <fafhrd91@gmail.com>
Project-URL: Homepage, https://github.com/PyO3/setuptools-rust
Project-URL: Repository, https://github.com/PyO3/setuptools-rust
Project-URL: Documentation, https://setuptools-rust.readthedocs.io
Project-URL: Changelog, https://github.com/PyO3/setuptools-rust/blob/main/CHANGELOG.md
Keywords: distutils,setuptools,rust
Classifier: Topic :: Software Development :: Version Control
Classifier: License :: OSI Approved :: MIT License
Classifier: Intended Audience :: Developers
Classifier: Programming Language :: Python :: 3
Classifier: Programming Language :: Python :: 3.8
Classifier: Programming Language :: Python :: 3.9
Classifier: Programming Language :: Python :: 3.10
Classifier: Programming Language :: Python :: 3.11
Classifier: Development Status :: 5 - Production/Stable
Classifier: Operating System :: POSIX
Classifier: Operating System :: MacOS :: MacOS X
Classifier: Operating System :: Microsoft :: Windows
Requires-Python: >=3.8
License-File: LICENSE
Requires-Dist: setuptools>=62.4
Requires-Dist: semantic_version<3,>=2.8.2
